dotfgen/__init__.py
dotfgen/__main__.py
dotfgen/cli.py
dotfgen-1.0.0a5.dist-info/LICENSE
dotfgen-1.0.0a5.dist-info/LICENSES/CC0-1.0.txt
dotfgen-1.0.0a5.dist-info/LICENSES/GPL-3.0-or-later.txt
dotfgen-1.0.0a5.dist-info/METADATA
dotfgen-1.0.0a5.dist-info/WHEEL
dotfgen-1.0.0a5.dist-info/entry_points.txt
dotfgen-1.0.0a5.dist-info/RECORD
